acd/__init__.py
acd/agglomeration/__init__.py
acd/agglomeration/agg_1d.py
acd/agglomeration/agg_2d.py
acd/scores/__init__.py
acd/scores/cd.py
acd/scores/cd_architecture_specific.py
acd/scores/cd_propagate.py
acd/scores/score_funcs.py
acd/util/__init__.py
acd/util/conv2dnp.py
acd/util/tiling_1d.py
acd/util/tiling_2d.py
acd-0.0.2.dist-info/LICENSE
acd-0.0.2.dist-info/METADATA
acd-0.0.2.dist-info/WHEEL
acd-0.0.2.dist-info/top_level.txt
acd-0.0.2.dist-info/RECORD
