Metadata-Version: 2.1
Name: acd
Version: 0.0.2
Summary: Hierarchical interpretatations and contextual decomposition in pytorch
Home-page: https://github.com/csinva/hierarchical-dnn-interpretations
Author: Chandan Singh
License: UNKNOWN
Platform: UNKNOWN
Classifier: Programming Language :: Python :: 3
Classifier: License :: OSI Approved :: MIT License
Classifier: Operating System :: OS Independent
Requires-Dist: scipy
Requires-Dist: numpy
Requires-Dist: scikit-image
Requires-Dist: torch
Requires-Dist: tqdm
